tokka-0.1.1b0.dist-info/METADATA
tokka-0.1.1b0.dist-info/WHEEL
tokka-0.1.1b0.dist-info/licenses/LICENSE
tokka/__init__.py
tokka/kwargs.py
tokka-0.1.1b0.dist-info/RECORD
