Metadata-Version: 2.1
Name: tokka
Version: 0.1.1b0
Summary: A thin async layer between Pydantic and MongoDB
Author-Email: ericmiguel <eric.mrib@gmail.com>
License: MIT
Requires-Python: >=3.12
Requires-Dist: motor>=3.4.0
Requires-Dist: pydantic>=2.7.0
Requires-Dist: pydantic-settings>=2.2.1
